loon/__init__.py
loon/cli.py
loon/parser.py
loon_parser-2.0.0.dist-info/METADATA
loon_parser-2.0.0.dist-info/WHEEL
loon_parser-2.0.0.dist-info/entry_points.txt
loon_parser-2.0.0.dist-info/top_level.txt
loon_parser-2.0.0.dist-info/RECORD
